mytower_etl/__init__.py
mytower_etl/extractors/__init__.py
mytower_etl/extractors/sftp_client.py
mytower_etl/loaders/__init__.py
mytower_etl/loaders/post_to_api.py
mytower_etl/transformers/__init__.py
mytower_etl/transformers/load_rule.py
mytower_etl/transformers/mapper.py
mytower_etl/utils/__init__.py
mytower_etl/utils/db_log_helper.py
mytower_etl/utils/file_utils.py
mytower_etl/utils/logging_utils.py
tests/__init__.py
tests/test_sftp_client.py
sdvetl-0.1.0.dist-info/LICENSE
sdvetl-0.1.0.dist-info/METADATA
sdvetl-0.1.0.dist-info/WHEEL
sdvetl-0.1.0.dist-info/top_level.txt
sdvetl-0.1.0.dist-info/RECORD
